baddns/__init__.py
baddns/base.py
baddns/cli.py
baddns/lib/__init__.py
baddns/lib/dnsmanager.py
baddns/lib/dnswalk.py
baddns/lib/errors.py
baddns/lib/findings.py
baddns/lib/httpmanager.py
baddns/lib/loader.py
baddns/lib/logging.py
baddns/lib/matcher.py
baddns/lib/signature.py
baddns/lib/whoismanager.py
baddns/modules/__init__.py
baddns/modules/cname.py
baddns/modules/mx.py
baddns/modules/ns.py
baddns/modules/nsec.py
baddns/modules/references.py
baddns/modules/txt.py
baddns/modules/zonetransfer.py
baddns/scripts/__init__.py
baddns/scripts/readsources.py
baddns/scripts/signaturetest.py
baddns/signatures/.gitignore
baddns/signatures/baddns_aws-bucket-website.yml
baddns/signatures/baddns_substack.yml
baddns/signatures/dnsreaper_000domains.yml
baddns/signatures/dnsreaper_agilecrm.yml
baddns/signatures/dnsreaper_aws_ns.yml
baddns/signatures/dnsreaper_bizland.yml
baddns/signatures/dnsreaper_brandpad.yml
baddns/signatures/dnsreaper_brightcove.yml
baddns/signatures/dnsreaper_campaign_monitor.yml
baddns/signatures/dnsreaper_cargo_collective.yml
baddns/signatures/dnsreaper_convertkit.yml
baddns/signatures/dnsreaper_digitalocean.yml
baddns/signatures/dnsreaper_dnsmadeeasy.yml
baddns/signatures/dnsreaper_dnssimple.yml
baddns/signatures/dnsreaper_domain.yml
baddns/signatures/dnsreaper_dotster.yml
baddns/signatures/dnsreaper_elastic_beanstalk.yml
baddns/signatures/dnsreaper_frontify.yml
baddns/signatures/dnsreaper_getresponse.yml
baddns/signatures/dnsreaper_github_pages.yml
baddns/signatures/dnsreaper_googlecloud.yml
baddns/signatures/dnsreaper_hatenablog.yml
baddns/signatures/dnsreaper_helpscout.yml
baddns/signatures/dnsreaper_hostinger.yml
baddns/signatures/dnsreaper_hurricane_electric.yml
baddns/signatures/dnsreaper_jetbrains.yml
baddns/signatures/dnsreaper_launchrock_cname.yml
baddns/signatures/dnsreaper_linode.yml
baddns/signatures/dnsreaper_mashery.yml
baddns/signatures/dnsreaper_mediatemplate.yml
baddns/signatures/dnsreaper_mysmartjobboard.yml
baddns-1.11.236.dist-info/METADATA
baddns-1.11.236.dist-info/WHEEL
baddns-1.11.236.dist-info/entry_points.txt
baddns-1.11.236.dist-info/licenses/LICENSE
baddns-1.11.236.dist-info/RECORD
