Metadata-Version: 2.4
Name: baddns
Version: 1.11.236
Summary: Check subdomains for subdomain takeovers and other DNS tomfoolery
License: GPL-3.0
License-File: LICENSE
Author: liquidsec
Author-email: paul.mueller08@gmail.com
Requires-Python: >=3.9,<4.0
Classifier: License :: OSI Approved :: GNU General Public License v3 (GPLv3)
Classifier: Programming Language :: Python :: 3
Classifier: Programming Language :: Python :: 3.9
Classifier: Programming Language :: Python :: 3.10
Classifier: Programming Language :: Python :: 3.11
Classifier: Programming Language :: Python :: 3.12
Classifier: Programming Language :: Python :: 3.13
Classifier: Programming Language :: Python :: 3.14
Requires-Dist: colorama (>=0.4.6,<0.5.0)
Requires-Dist: dnspython (>=2.4.2,<3.0.0)
Requires-Dist: httpx (>=0.27.0,<0.29.0)
Requires-Dist: python-dateutil (==2.9.0.post0)
Requires-Dist: python-whois (>=0.9.5,<0.10.0)
Requires-Dist: pyyaml (>=6.0.1,<7.0.0)
Requires-Dist: tldextract (>=5.1.1,<6.0.0)
Project-URL: Documentation, https://www.blacklanternsecurity.com/baddns/
Project-URL: Homepage, https://github.com/blacklanternsecurity/baddns
Project-URL: Repository, https://github.com/blacklanternsecurity/baddns
